[
  {
    "Nombre": "Mamá",
    "AporteLuz": 0,
    "AporteGas": 0,
    "AporteInternet": 0,
    "AporteComida": 0
  },
  {
    "Nombre": "Papá",
    "AporteLuz": 0,
    "AporteGas": 0,
    "AporteInternet": 0,
    "AporteComida": 0
  },
  {
    "Nombre": "Franco",
    "AporteLuz": 0,
    "AporteGas": 0,
    "AporteInternet": 0,
    "AporteComida": 0
  },
  {
    "Nombre": "Leo",
    "AporteLuz": 0,
    "AporteGas": 0,
    "AporteInternet": 0,
    "AporteComida": 0
  }
]